announceexctractor/__init__.py
announceexctractor/main.py
announceexctractor/prompts.py
announceexctractor-2025.12.21121449.dist-info/METADATA
announceexctractor-2025.12.21121449.dist-info/WHEEL
announceexctractor-2025.12.21121449.dist-info/top_level.txt
announceexctractor-2025.12.21121449.dist-info/RECORD
