Metadata-Version: 2.4
Name: announceexctractor
Version: 2025.12.21121449
Summary: The package helps users extract key details from short announcements or descriptions. It focuses on understanding the core offering and any associated benefits presented in plain text, without needing
Author-email: announceexctractor <hi@eugene.plus>
License: MIT
Project-URL: Homepage, https://github.com/chigwell/announceexctractor
Requires-Python: >=3.9
Requires-Dist: langchain-llm7>=0.0.0
Requires-Dist: llmatch-messages>=0.0.0
Requires-Dist: langchain-core>=0.3.0
